neutral_ai/__init__.py
neutral_ai/neutral_ai.py
neutral_ai/py.typed
neutral_ai-0.1.0.dist-info/METADATA
neutral_ai-0.1.0.dist-info/WHEEL
neutral_ai-0.1.0.dist-info/entry_points.txt
neutral_ai-0.1.0.dist-info/licenses/LICENSE
neutral_ai-0.1.0.dist-info/RECORD
